AudioAugmentor/__init__.py
AudioAugmentor/core.py
AudioAugmentor/rir_setup.py
AudioAugmentor/sox_parser.py
AudioAugmentor/torchaudio_transf_wrapper.py
AudioAugmentor/transf_gen.py
AudioAugmentor-0.1.1.dist-info/LICENSE
AudioAugmentor-0.1.1.dist-info/METADATA
AudioAugmentor-0.1.1.dist-info/WHEEL
AudioAugmentor-0.1.1.dist-info/top_level.txt
AudioAugmentor-0.1.1.dist-info/RECORD
