Metadata-Version: 2.1
Name: AudioAugmentor
Version: 0.1.1
Summary: Python package for simple application of wide range of audio augmentations.
Author-email: Ladislav Vašina <ladislavvasina@gmail.com>
License: MIT License
Project-URL: Homepage, https://github.com/LadislavVasina1/AudioAugmentor_public
Project-URL: Repository, https://github.com/LadislavVasina1/AudioAugmentor_public
Project-URL: Issues, https://github.com/LadislavVasina1/AudioAugmentor_public/issues
Keywords: audio,augmentation,pytorch,machine learning,deep learning,data augmentation,audio processing,audio augmentation,audio data augmentation,audio data processing,torchaudio,ffmpeg,ffmpeg-python,audiomentations,torch-audiomentations,RIR,room impulse response,room simulation,pyroomacoustics
Classifier: Intended Audience :: Developers
Classifier: License :: OSI Approved :: MIT License
Classifier: Programming Language :: Python
Classifier: Programming Language :: Python :: 3
Classifier: Programming Language :: Python :: 3.10
Classifier: Programming Language :: Python :: 3.11
Requires-Python: >=3.10
License-File: LICENSE
Requires-Dist: audiomentations ==0.34.1
Requires-Dist: audiomentations[extras]
Requires-Dist: datasets ==2.17.1
Requires-Dist: ffmpeg-python ==0.2.0
Requires-Dist: huggingface-hub ==0.20.3
Requires-Dist: ipython ==8.12.3
Requires-Dist: matplotlib ==3.8.3
Requires-Dist: numpy ==1.24.4
Requires-Dist: pyroomacoustics ==0.7.3
Requires-Dist: PyYAML ==6.0.1
Requires-Dist: SciPy ==1.10.1
Requires-Dist: soundfile ==0.12.1
Requires-Dist: torch ==2.2.0
Requires-Dist: torch-audiomentations ==0.11.1
Requires-Dist: torchaudio ==2.2.0
Requires-Dist: transformers
Requires-Dist: pydub
Requires-Dist: accelerate
Requires-Dist: soundfile
Requires-Dist: librosa
Requires-Dist: evaluate
Requires-Dist: jiwer
Requires-Dist: tensorboard
Requires-Dist: gradio
Requires-Dist: ffmpeg-python
Requires-Dist: torch-pitch-shift
Requires-Dist: julius
Requires-Dist: tqdm
Requires-Dist: shapely
Requires-Dist: py-heat-magic
